[
	{
		"type" : "key",
		"cmd" : [
			{
				"dur" : 30,
				"key" : "w"
			}
		]
	},
	{
		"type" : "key",
		"cmd" : [
			{
				"dur" : 30,
				"key" : "d"
			}
		]
	},
	{
		"type" : "comment",
		"cmd" : "this is a comment"
	},
	{
		"type" : "key",
		"cmd" : [
			{
				"dur" : 60,
				"key" : "w"
			},
			{
				"dur" : 180,
				"key" : "a"
			},
			{
				"dur" : 240,
				"key" : "d"
			}
		]
	},
	{
		"type" : "key",
		"cmd" : [
			{
				"dur" : 69,
				"key" : "j"
			}
		]
	},
	{
		"type" : "key",
		"cmd" : [
			{
				"dur" : 130,
				"key" : "f"
			}
		]
	},
	{
		"type" : "key",
		"cmd" : [
			{
				"dur" : 75,
				"key" : "a"
			}
		]
	},
	{
		"type" : "key",
		"cmd" : [
			{
				"dur" : 60,
				"key" : "j"
			},
			{
				"dur" : 180,
				"key" : "w"
			},
			{
				"dur" : 240,
				"key" : "a"
			}
		]
	}
]
